Metadata-Version: 2.1
Name: sauron-doc-rotation
Version: 0.1.0
Summary: Fix rotation in images
Home-page: https://github.com/modestoo/sauron-doc-rotation.git
Download-URL: https://github.com
Author: Augusto Modesto
License: MIT
Keywords: image-processing,image-rotation,rotation,text
Classifier: Intended Audience :: Information Technology
Classifier: Natural Language :: English
Classifier: Operating System :: POSIX :: Linux
Classifier: Programming Language :: Python :: 3.10
Requires-Python: ==3.10.*
License-File: LICENSE.md
Requires-Dist: numpy==2.0.0
Requires-Dist: scikit-image==0.24.0
Requires-Dist: scipy==1.14.0
Requires-Dist: matplotlib==3.9.0
Requires-Dist: pytesseract==0.3.10
Requires-Dist: opencv-python==4.10.0.84
Requires-Dist: imutils==0.5.4
Requires-Dist: loguru==0.7.2
